{"MwsYgMqP69fZubfVCct86w==":"whatsapp%20image%202023-04-14%20at%2011.24.25-815x1087.jpg","1Z4RomV6SYP5wTADNXJqHQ==":"%D7%A1%D7%A4%D7%99%D7%A8-224x224.png","or9Z36oW8ZwV1j3TZ/lp6Q==":"%D7%A1%D7%A4%D7%99%D7%A8-224x224.png","911X7bM4yT2Mobv6BsMc+g==":"background8.jpg","toErpZOpoUxgxg2wFXh9Dw==":"5.jpg","oRykAiO0rUD++7AmPeEwUg==":"background1.jpg","n1dx+NZv3qks526xC0hZ5Q==":"background13.jpg","tV4LcLO/TlCTxYDwLrUS/w==":"node-815x499.jpg","6j6OeYqV28yoPS6SGevaew==":"react-815x452.jpg","vFRF5Ua/qsVQZWO70NpWPw==":"mongodb-815x220.jpg","zo6PERZIJ047wNTnfbfIPw==":"whatsapp%20image%202019-12-06%20at%2011.37.04-640x640.jpg","cgY6mLr2WowH2KsKeLDGaQ==":"whatsapp%20image%202019-12-06%20at%2011.37.04-640x640.jpeg","iIuSuxsTS/puLEPJvU35Kw==":"%D7%A8%D7%95%D7%A2%D7%99-815x763.jpg","+/Zbs+Uq1KwNc9Hp6RGb5g==":"%D7%A8%D7%95%D7%A2%D7%99-815x865.jpg","2ZxjsKefZYEttBa+ui0W2g==":"%D7%A8%D7%95%D7%A2%D7%99-815x810.jpg"}